RobotEyes/__init__.py
RobotEyes/constants.py
RobotEyes/imagemagick.py
RobotEyes/report_generator.py
RobotEyes/report_utils.py
RobotEyes/reportgen.py
RobotEyes/runner.py
RobotEyes/selenium_hooks.py
RobotEyes/web.py
RobotEyes/templates/base.html
RobotEyes/templates/failed.html
RobotEyes/templates/overview.html
RobotEyes/templates/passed.html
RobotEyes/templates/report.html
RobotEyes/templates/test.html
robotframework_eyes-1.6.2.dist-info/LICENSE
robotframework_eyes-1.6.2.dist-info/METADATA
robotframework_eyes-1.6.2.dist-info/WHEEL
robotframework_eyes-1.6.2.dist-info/entry_points.txt
robotframework_eyes-1.6.2.dist-info/top_level.txt
robotframework_eyes-1.6.2.dist-info/RECORD
