Metadata-Version: 2.1
Name: robotframework-eyes
Version: 1.6.2
Summary: Visual regression library and report generator for robot framework
Home-page: https://github.com/jz-jess/RobotEyes
Author: Jesse Zacharias
Author-email: iamjess988@gmail.com
License: MIT
Keywords: visual-regression image-comparison robotframework robot-eyes
Classifier: Framework :: Robot Framework
Classifier: Programming Language :: Python
Classifier: Topic :: Software Development :: Testing
License-File: LICENSE
Requires-Dist: pillow
Requires-Dist: robotframework
Requires-Dist: flask
